MANIFEST.in
README.rst
requirements.txt
setup.py
uestc/__init__.py
uestc/catch_course.py
uestc/encrypt.py
uestc/exceptions.py
uestc/login.py
uestc/query.py
uestc.egg-info/PKG-INFO
uestc.egg-info/SOURCES.txt
uestc.egg-info/dependency_links.txt
uestc.egg-info/requires.txt
uestc.egg-info/top_level.txt