Metadata-Version: 1.2
Name: uestc
Version: 1.2.2
Summary: 一个和电子科大有关的模块
Home-page: https://github.com/plusls/uestc
Author: plusls<plusls@qq.com>
Author-email: plusls@qq.com
Maintainer: plusls<plusls@qq.com>
License: UNKNOWN
Keywords: uestc catch course login
Platform: UNKNOWN
Classifier: Environment :: Console
Classifier: Programming Language :: Python :: 3
Classifier: Programming Language :: Python :: 3.3
Classifier: Programming Language :: Python :: 3.4
Classifier: Programming Language :: Python :: 3.5
Classifier: Programming Language :: Python :: 3.6
Classifier: Programming Language :: Python :: 3.7
Classifier: Topic :: Internet :: WWW/HTTP
Classifier: Topic :: Software Development :: Libraries :: Python Modules
